ResponsePrediction/__init__.py
ResponsePrediction/_deterministic.py
ResponsePrediction/_stochastic.py
ResponsePrediction/_tools.py
ResponsePrediction-0.0.5.dist-info/LICENSE
ResponsePrediction-0.0.5.dist-info/METADATA
ResponsePrediction-0.0.5.dist-info/WHEEL
ResponsePrediction-0.0.5.dist-info/top_level.txt
ResponsePrediction-0.0.5.dist-info/RECORD
