Metadata-Version: 2.1
Name: ResponsePrediction
Version: 0.0.5
Summary: Vessel wave-induced response prediction
Author-email: Jan-Erik Hygen <j-e.hygen@hotmail.com>
License: GNU GENERAL PUBLIC LICENSE
Keywords: deterministic,FFT,autocorrelation,marine,vessel,RAO,response,waves
Classifier: Programming Language :: Python :: 3
Requires-Python: >=3.9
License-File: LICENSE
Requires-Dist: scipy
Requires-Dist: numpy
Requires-Dist: matplotlib
